openean/Item.py
openean/OpenEAN.py
openean/RequestStatus.py
openean/__init__.py
openean-0.1.2.dist-info/LICENSE
openean-0.1.2.dist-info/METADATA
openean-0.1.2.dist-info/WHEEL
openean-0.1.2.dist-info/top_level.txt
openean-0.1.2.dist-info/RECORD
