Metadata-Version: 2.1
Name: openean
Version: 0.1.2
Summary: Unofficial API wrapper for Open EAN/GTIN Database
Home-page: https://github.com/DavidM42/OpenEAN
Author: DavidM42
Author-email: david@merz.dev
License: MIT
Platform: UNKNOWN
Classifier: Programming Language :: Python :: 3
Classifier: License :: OSI Approved :: MIT License
Classifier: Operating System :: OS Independent
Requires-Dist: requests
